job_crawler/__init__.py
job_crawler/cli.py
job_crawler/export.py
job_crawler/gemini_crawler.py
job_crawler/generic_job.py
job_crawler/topcv.py
job_crawler/vietnamworks.py
job_crawler/database/__init__.py
job_crawler/database/_init_db.py
job_crawler/database/connection.py
job_crawler/database/handlers.py
job_crawler/database/models.py
job_crawler/database/sql.py
job_crawler/utils/email_service.py
job_crawler/utils/enums.py
job_crawler/utils/logger.py
job_crawler/utils/notification_handler.py
ghibli_job_crawler-0.2.0.dist-info/METADATA
ghibli_job_crawler-0.2.0.dist-info/WHEEL
ghibli_job_crawler-0.2.0.dist-info/entry_points.txt
ghibli_job_crawler-0.2.0.dist-info/top_level.txt
ghibli_job_crawler-0.2.0.dist-info/RECORD
