Metadata-Version: 2.4
Name: ghibli_job_crawler
Version: 0.2.0
Summary: Add your description here
Requires-Python: >=3.10
Requires-Dist: beautifulsoup4>=4.14.2
Requires-Dist: google-genai>=1.50.1
Requires-Dist: mysql-connector-python>=9.5.0
Requires-Dist: playwright>=1.56.0
Requires-Dist: psycopg2>=2.9.11
Requires-Dist: python-dotenv>=1.2.1
Requires-Dist: requests>=2.32.5
